focus_opt/__init__.py
focus_opt/config_candidate.py
focus_opt/helpers.py
focus_opt/hp_space.py
focus_opt/optimizers.py
tests/__init__.py
tests/test_config_candidate.py
tests/test_hp_space.py
tests/test_opt.py
focus_opt-0.1.0.dist-info/LICENSE
focus_opt-0.1.0.dist-info/METADATA
focus_opt-0.1.0.dist-info/WHEEL
focus_opt-0.1.0.dist-info/top_level.txt
focus_opt-0.1.0.dist-info/RECORD
