Metadata-Version: 2.1
Name: focus_opt
Version: 0.1.0
Summary: Multi-fidelity optimisation
Home-page: https://github.com/eliottkalfon/focus-opt
Author: Eliott Kalfon
Author-email: eliott.kalfon@gmail.com
Classifier: Programming Language :: Python :: 3
Classifier: License :: OSI Approved :: Apache Software License
Classifier: Operating System :: OS Independent
Requires-Python: >=3.8
License-File: LICENSE
Requires-Dist: numpy
